epct/None.py
epct/__init__.py
epct/_nbdev.py
epct/configs.py
epct/evolvers.py
epct/examples.py
epct/properties.py
epct/structure.py
epct-0.0.1.dist-info/LICENSE
epct-0.0.1.dist-info/METADATA
epct-0.0.1.dist-info/WHEEL
epct-0.0.1.dist-info/entry_points.txt
epct-0.0.1.dist-info/top_level.txt
epct-0.0.1.dist-info/RECORD
