Metadata-Version: 2.1
Name: epct
Version: 0.0.1
Summary: Evolutionary approach to constructing PCT hierarchies
Home-page: https://github.com/perceptualrobots/epct/tree/master/
Author: Rupert Young
Author-email: rupert@perceptualrobots.com
License: Apache Software License 2.0
Keywords: pct,control systems,robotics,psychology,deep learning,genetic algorithms,evolutionary algorithms
Platform: UNKNOWN
Classifier: Development Status :: 3 - Alpha
Classifier: Intended Audience :: Developers
Classifier: License :: OSI Approved :: Apache Software License
Classifier: Natural Language :: English
Classifier: Programming Language :: Python :: 3.6
Classifier: Programming Language :: Python :: 3.7
Classifier: Programming Language :: Python :: 3.8
Requires-Python: >=3.6
Requires-Dist: plotly
Requires-Dist: numpy
Requires-Dist: gym
Requires-Dist: networkx
Requires-Dist: matplotlib
Requires-Dist: graphviz
Requires-Dist: deap
Requires-Dist: pct
Requires-Dist: jproperties
